<HBProfile>
	<Name></Name>
	<MinDurability>0.3</MinDurability>
	<MinFreeBagSlots>3</MinFreeBagSlots>
 
	<MinLevel>1</MinLevel>
	<MaxLevel>86</MaxLevel>
	<Factions>99999</Factions>
 
	<MailGrey>false</MailGrey>
	<MailWhite>True</MailWhite>
	<MailGreen>True</MailGreen>
	<MailBlue>True</MailBlue>
	<MailPurple>True</MailPurple>
 
	<SellGrey>false</SellGrey>
	<SellWhite>false</SellWhite>
	<SellGreen>false</SellGreen>
	<SellBlue>false</SellBlue>
	<SellPurple>false</SellPurple>
	<Vendors>
	</Vendors>
	<Mailboxes>
	</Mailboxes>
	<Hotspots>
	<Hotspot X="3447.96" Y="3839.98" Z="149.558" />
	<Hotspot X="3547.38" Y="3731.83" Z="133.255" />
	<Hotspot X="3599.14" Y="3577.34" Z="129.483" />
	<Hotspot X="3382.76" Y="3561.89" Z="159.123" />
	<Hotspot X="2982.9" Y="3125" Z="126.077" />
	<Hotspot X="2974.98" Y="3269.81" Z="143.159" />
	<Hotspot X="3139.22" Y="3459.41" Z="110.957" />
	<Hotspot X="3182.84" Y="3950.5" Z="173.32" />
	<Hotspot X="3095.78" Y="4055.24" Z="150.89" />
	<Hotspot X="2941.37" Y="4403.07" Z="125.204" />
	<Hotspot X="2590.97" Y="4350.27" Z="134.926" />
	<Hotspot X="2751.38" Y="4152.16" Z="190.474" />
	<Hotspot X="2769.93" Y="3939.95" Z="147.018" />
	<Hotspot X="2883.98" Y="3787.18" Z="171.006" />
	<Hotspot X="2687.35" Y="3722.97" Z="148.994" />
	<Hotspot X="2706.27" Y="3521.64" Z="144.135" />
	<Hotspot X="2530.76" Y="3414.56" Z="136.92" />
	<Hotspot X="2776.69" Y="2918.54" Z="124.609" />
	<Hotspot X="3052.74" Y="2840.94" Z="106.076" />
	<Hotspot X="3260.71" Y="2702.03" Z="155.001" />
	<Hotspot X="3251.77" Y="2609.67" Z="142.504" />
	<Hotspot X="3350.16" Y="2317.67" Z="94.0603" />
	<Hotspot X="3286.94" Y="2298.71" Z="112.738" />
	<Hotspot X="3092.26" Y="2185.03" Z="154.221" />
	<Hotspot X="3244.59" Y="2112.57" Z="136.2" />
	<Hotspot X="2974.94" Y="2310" Z="166.597" />
	<Hotspot X="2616.51" Y="2441.82" Z="109.404" />
	<Hotspot X="2556.84" Y="2513.5" Z="123.254" />
	<Hotspot X="2642.23" Y="2606.78" Z="122.527" />
	<Hotspot X="2520.22" Y="2760.72" Z="137.16" />
	<Hotspot X="2495.54" Y="2828.56" Z="142.792" />
	<Hotspot X="2388.82" Y="2907.37" Z="139.726" />
	<Hotspot X="2248.79" Y="2634.99" Z="114.038" />
	<Hotspot X="2163.16" Y="2375.29" Z="95.3416" />
	<Hotspot X="2156.3" Y="2199.73" Z="75.5539" />
	<Hotspot X="2248.25" Y="2138.87" Z="81.2446" />
	<Hotspot X="2447.78" Y="2261.46" Z="130.211" />
	<Hotspot X="2417.6" Y="2139.08" Z="92.7451" />
	<Hotspot X="2505.52" Y="2062.02" Z="96.5479" />
	<Hotspot X="3061.61" Y="1927.51" Z="149.578" />
	<Hotspot X="3199.59" Y="1740.3" Z="137.098" />
	<Hotspot X="3212.48" Y="1749.42" Z="134.513" />
	<Hotspot X="3249.33" Y="1944.17" Z="137.512" />
	<Hotspot X="3584.32" Y="1986.03" Z="107.019" />
	<Hotspot X="3621.26" Y="2114.16" Z="110.9" />
	<Hotspot X="3703.02" Y="2224.27" Z="129.298" />
	<Hotspot X="3786.64" Y="1981.48" Z="262.998" />
	<Hotspot X="3864.28" Y="2092.68" Z="260.235" />
	<Hotspot X="3927.25" Y="2180.58" Z="240.274" />
	<Hotspot X="4001.63" Y="2237.25" Z="168.234" />
	<Hotspot X="4039.54" Y="2293.89" Z="117.988" />
	<Hotspot X="4160.79" Y="2214.92" Z="175.028" />
	<Hotspot X="4040.15" Y="2061.01" Z="258.764" />
	<Hotspot X="3996.17" Y="1894.34" Z="252.22" />
	<Hotspot X="3920.34" Y="1788.16" Z="234.466" />
	<Hotspot X="3684.01" Y="1754.31" Z="132.285" />
	<Hotspot X="3754.12" Y="1632.7" Z="193" />
	<Hotspot X="3756.841" Y="1628.505" Z="193" />
	<Hotspot X="3759.562" Y="1624.31" Z="192" />
	<Hotspot X="3762.283" Y="1620.115" Z="191" />
	<Hotspot X="3765.004" Y="1615.921" Z="190" />
	<Hotspot X="3767.725" Y="1611.726" Z="189" />
	<Hotspot X="3770.446" Y="1607.531" Z="188" />
	<Hotspot X="3773.167" Y="1603.336" Z="187" />
	<Hotspot X="3778.609" Y="1594.947" Z="186" />
	<Hotspot X="3781.33" Y="1590.752" Z="185" />
	<Hotspot X="3784.051" Y="1586.557" Z="183" />
	<Hotspot X="3754.12" Y="1632.7" Z="138.88" />
	<Hotspot X="3857.93" Y="1472.66" Z="-76" />
	<Hotspot X="3862.781" Y="1471.447" Z="-73" />
	<Hotspot X="3867.631" Y="1470.233" Z="-71" />
	<Hotspot X="3872.481" Y="1469.02" Z="-70" />
	<Hotspot X="3877.332" Y="1467.806" Z="-69" />
	<Hotspot X="3882.183" Y="1466.593" Z="-69" />
	<Hotspot X="3887.033" Y="1465.379" Z="-68" />
	<Hotspot X="3891.884" Y="1464.166" Z="-66" />
	<Hotspot X="3896.734" Y="1462.952" Z="-59" />
	<Hotspot X="3901.584" Y="1461.739" Z="-58" />
	<Hotspot X="3906.435" Y="1460.525" Z="-61" />
	<Hotspot X="3911.286" Y="1459.312" Z="-60" />
	<Hotspot X="3916.136" Y="1458.099" Z="-53" />
	<Hotspot X="3920.987" Y="1456.885" Z="-35" />
	<Hotspot X="3925.837" Y="1455.672" Z="-26" />
	<Hotspot X="3930.688" Y="1454.458" Z="-23" />
	<Hotspot X="3935.538" Y="1453.245" Z="-24" />
	<Hotspot X="3940.389" Y="1452.031" Z="-31" />
	<Hotspot X="3945.239" Y="1450.818" Z="-41" />
	<Hotspot X="3950.09" Y="1449.604" Z="-48" />
	<Hotspot X="3954.94" Y="1448.391" Z="-60" />
	<Hotspot X="3959.791" Y="1447.177" Z="-65" />
	<Hotspot X="3964.641" Y="1445.964" Z="-65" />
	<Hotspot X="3969.492" Y="1444.75" Z="-65" />
	<Hotspot X="3974.342" Y="1443.537" Z="-64" />
	<Hotspot X="3979.193" Y="1442.323" Z="-64" />
	<Hotspot X="3984.043" Y="1441.11" Z="-63" />
	<Hotspot X="3988.894" Y="1439.896" Z="-63" />
	<Hotspot X="3993.744" Y="1438.683" Z="-63" />
	<Hotspot X="3998.595" Y="1437.47" Z="-64" />
	<Hotspot X="4003.445" Y="1436.256" Z="-67" />
	<Hotspot X="4008.296" Y="1435.043" Z="-66" />
	<Hotspot X="4013.146" Y="1433.829" Z="-65" />
	<Hotspot X="4017.997" Y="1432.616" Z="-64" />
	<Hotspot X="4022.847" Y="1431.402" Z="-64" />
	<Hotspot X="4027.698" Y="1430.189" Z="-64" />
	<Hotspot X="4032.549" Y="1428.975" Z="-64" />
	<Hotspot X="4037.399" Y="1427.762" Z="-63" />
	<Hotspot X="4042.25" Y="1426.548" Z="-63" />
	<Hotspot X="4047.1" Y="1425.335" Z="-63" />
	<Hotspot X="4051.951" Y="1424.121" Z="-63" />
	<Hotspot X="4056.801" Y="1422.908" Z="-62" />
	<Hotspot X="4061.652" Y="1421.695" Z="-63" />
	<Hotspot X="4066.502" Y="1420.481" Z="-64" />
	<Hotspot X="4071.353" Y="1419.268" Z="-64" />
	<Hotspot X="4076.203" Y="1418.054" Z="-61" />
	<Hotspot X="4081.054" Y="1416.841" Z="-60" />
	<Hotspot X="4085.904" Y="1415.627" Z="-59" />
	<Hotspot X="4090.755" Y="1414.414" Z="-58" />
	<Hotspot X="4095.605" Y="1413.2" Z="-58" />
	<Hotspot X="4100.456" Y="1411.987" Z="-59" />
	<Hotspot X="4105.306" Y="1410.773" Z="-60" />
	<Hotspot X="4110.157" Y="1409.56" Z="-60" />
	<Hotspot X="4115.007" Y="1408.347" Z="-60" />
	<Hotspot X="4119.858" Y="1407.133" Z="-60" />
	<Hotspot X="4124.708" Y="1405.92" Z="-61" />
	<Hotspot X="4129.559" Y="1404.706" Z="-61" />
	<Hotspot X="4134.409" Y="1403.493" Z="-59" />
	<Hotspot X="4139.26" Y="1402.279" Z="-59" />
	<Hotspot X="3857.93" Y="1472.66" Z="-131.223" />
	<Hotspot X="4128.335" Y="1558.59" Z="85" />
	<Hotspot X="4127.697" Y="1563.549" Z="102" />
	<Hotspot X="4127.059" Y="1568.508" Z="109" />
	<Hotspot X="4126.42" Y="1573.467" Z="112" />
	<Hotspot X="4125.781" Y="1578.426" Z="111" />
	<Hotspot X="4125.143" Y="1583.385" Z="111" />
	<Hotspot X="4124.504" Y="1588.344" Z="111" />
	<Hotspot X="4123.866" Y="1593.303" Z="119" />
	<Hotspot X="4123.227" Y="1598.262" Z="145" />
	<Hotspot X="4122.588" Y="1603.221" Z="168" />
	<Hotspot X="4121.95" Y="1608.18" Z="173" />
	<Hotspot X="4121.312" Y="1613.139" Z="175" />
	<Hotspot X="4120.673" Y="1618.098" Z="177" />
	<Hotspot X="4120.034" Y="1623.057" Z="179" />
	<Hotspot X="4119.396" Y="1628.016" Z="178" />
	<Hotspot X="4118.757" Y="1632.976" Z="178" />
	<Hotspot X="4118.119" Y="1637.935" Z="181" />
	<Hotspot X="4117.48" Y="1642.894" Z="184" />
	<Hotspot X="4116.841" Y="1647.853" Z="185" />
	<Hotspot X="4116.203" Y="1652.812" Z="186" />
	<Hotspot X="4115.564" Y="1657.771" Z="188" />
	<Hotspot X="4114.926" Y="1662.73" Z="188" />
	<Hotspot X="4114.287" Y="1667.689" Z="189" />
	<Hotspot X="4113.648" Y="1672.648" Z="190" />
	<Hotspot X="4113.01" Y="1677.607" Z="190" />
	<Hotspot X="4148.77" Y="1399.9" Z="-116.048" />
	<Hotspot X="4112" Y="1685.45" Z="137.024" />
	<Hotspot X="4310.58" Y="1853.46" Z="128.629" />
	<Hotspot X="4551" Y="2297.86" Z="146.322" />
	<Hotspot X="4817.3" Y="2388.41" Z="124.548" />
	<Hotspot X="4714.1" Y="2529.32" Z="240.431" />
	<Hotspot X="4811.17" Y="2713.62" Z="91.4097" />
	<Hotspot X="4837.52" Y="2900.81" Z="150.108" />
	<Hotspot X="4856.01" Y="3117.19" Z="119.864" />
	<Hotspot X="4875.08" Y="3286.09" Z="130.695" />
	<Hotspot X="4719.58" Y="3493.48" Z="129.992" />
	<Hotspot X="4718.5" Y="2982.96" Z="131.693" />
	<Hotspot X="4512.42" Y="2764.54" Z="149.444" />
	<Hotspot X="4539.29" Y="2676.24" Z="181.44" />
	<Hotspot X="4449.06" Y="2492.18" Z="100.3095" />
	<Hotspot X="4125.31" Y="2708.56" Z="110.451" />
	<Hotspot X="3974.76" Y="2413" Z="116.497" />
	<Hotspot X="3792.85" Y="2459.95" Z="121.729" />
	<Hotspot X="3614.22" Y="2342.14" Z="92.3628" />
	<Hotspot X="3419.57" Y="2652.58" Z="161.247" />
	<Hotspot X="3610.48" Y="2737.97" Z="152.736" />
	<Hotspot X="3329.11" Y="3122.41" Z="123.849" />
	<Hotspot X="3491.45" Y="3249.35" Z="107.823" />
	<Hotspot X="3877.01" Y="3341.06" Z="123.451" />
	<Hotspot X="4278.52" Y="3574.56" Z="143.15" />
	<Hotspot X="4494.89" Y="3571.03" Z="135.624" />
	<Hotspot X="4370.91" Y="3693.32" Z="106.836" />
	<Hotspot X="4039.78" Y="3747.54" Z="126.488" />
	<Hotspot X="4098.08" Y="3934.17" Z="194.653" />
	<Hotspot X="4162.85" Y="3943.63" Z="130.606" />
	<Hotspot X="4039.28" Y="4150.33" Z="198.02" />
	<Hotspot X="3902.5" Y="4084.73" Z="194.979" />
	<Hotspot X="3815.71" Y="4206.92" Z="118.063" />
	<Hotspot X="3512.23" Y="4053.59" Z="127.531" />
	<Hotspot X="3316.76" Y="4046.62" Z="161.215" />
	<Hotspot X="3335.47" Y="3939.41" Z="192.21" />
	</Hotspots>
	<Blackspots>
	<Blackspot X="3885.42" Y="4054.53" Z="121.332" Radius="15"  />
	<Blackspot X="4097.51" Y="4014.54" Z="117.968" Radius="15"  />
	<Blackspot X="3970.73" Y="4003.81" Z="117.861" Radius="15"  />
	<Blackspot X="4026.36" Y="3991.73" Z="126.466" Radius="15"  />
	<Blackspot X="4014.32" Y="3897.03" Z="122.53" Radius="15"  />
	<Blackspot X="3875.19" Y="2157.12" Z="139.215" Radius="15"  />
	<Blackspot X="3818.35" Y="2108.47" Z="148.726" Radius="15"  />
	<Blackspot X="3871.35" Y="2093.78" Z="132.057" Radius="15"  />
	<Blackspot X="3949.62" Y="4072.21" Z="122.184" Radius="15"  />
	<Blackspot X="3892.2" Y="2098.85" Z="155.421" Radius="15"  />
	<Blackspot X="3915.79" Y="2069.66" Z="132.531" Radius="15"  />
	<Blackspot X="4014.32" Y="3897.03" Z="122.53" Radius="15"  />
	<Blackspot X="4003.63" Y="3952.31" Z="126.057" Radius="15"  />
	<Blackspot X="3934.75" Y="3983.07" Z="123.159" Radius="15"  />
	<Blackspot X="4003.63" Y="3952.31" Z="126.057" Radius="15"  />
	<Blackspot X="3818.35" Y="2108.47" Z="148.726" Radius="15"  />
	<Blackspot X="3901.12" Y="2130.77" Z="137.718" Radius="15"  />
	<Blackspot X="3849.88" Y="2041.08" Z="144.354" Radius="15"  />
	<Blackspot X="3901.38" Y="2028.1" Z="150.577" Radius="15"  />
	<Blackspot X="3871.35" Y="2093.78" Z="132.057" Radius="15"  />
	<Blackspot X="3830.93" Y="2169.32" Z="144.845" Radius="15"  />
	<Blackspot X="3934.75" Y="3983.07" Z="123.159" Radius="15"  />
	<Blackspot X="4026.36" Y="3991.73" Z="126.466" Radius="15"  />
	<Blackspot X="3901.38" Y="2028.1" Z="150.577" Radius="15"  />
	<Blackspot X="3915.79" Y="2069.66" Z="132.531" Radius="15"  />
	<Blackspot X="3949.62" Y="4072.21" Z="122.184" Radius="15"  />
	<Blackspot X="4132.01" Y="3986.68" Z="118.732" Radius="15"  />
	<Blackspot X="3925.57" Y="3956.7" Z="125.109" Radius="15"  />
	<Blackspot X="3885.42" Y="4054.53" Z="121.332" Radius="15"  />
	<Blackspot X="3901.12" Y="2130.77" Z="137.718" Radius="15"  />
	</Blackspots>
</HBProfile>
